{
  "model": "timesfm2p5",
  "dataset": "Coastal_T_S_15T",
  "method": "BM",
  "ratio": 0.3,
  "term": "long",
  "imputation_method": "forward",
  "n_windows": 20,
  "period": 96,
  "summary": {
    "mean": {
      "trend_strength": 0.8316553919007543,
      "trend_linearity": 4.6960017556638755e-07,
      "seasonal_strength": 0.0742182622149263,
      "seasonal_correlation": 0.5278938279429662,
      "residual_autocorr_lag1": 0.8934531298336736,
      "spectral_entropy": -2680.561698411535
    },
    "std": {
      "trend_strength": 0.16532057841116463,
      "trend_linearity": 4.9207693466703005e-05,
      "seasonal_strength": 0.13017461103625735,
      "seasonal_correlation": 0.16019717191651298,
      "residual_autocorr_lag1": 0.0743922862695394,
      "spectral_entropy": 612.4075543054937
    },
    "min": {
      "trend_strength": 0.43736033534304986,
      "trend_linearity": -4.872923125092953e-05,
      "seasonal_strength": 0.0,
      "seasonal_correlation": 0.17603710883996557,
      "residual_autocorr_lag1": 0.7583664676770011,
      "spectral_entropy": -3914.1164574994427
    },
    "max": {
      "trend_strength": 0.9965164109895047,
      "trend_linearity": 0.00019325407121691227,
      "seasonal_strength": 0.5409669909628683,
      "seasonal_correlation": 0.9465558614336386,
      "residual_autocorr_lag1": 0.9895246963567068,
      "spectral_entropy": -1402.3330009482024
    }
  }
}