{
  "model": "timesfm2p5",
  "dataset": "current_velocity_15T",
  "method": "clean",
  "ratio": null,
  "term": "long",
  "imputation_method": null,
  "n_windows": 15,
  "period": 96,
  "summary": {
    "mean": {
      "trend_strength": 0.891824586178941,
      "trend_linearity": -3.163398316360681e-05,
      "seasonal_strength": 0.03305998688997735,
      "seasonal_correlation": 0.5014770585404625,
      "residual_autocorr_lag1": 0.8275717176139973,
      "spectral_entropy": -2344.561021365959
    },
    "std": {
      "trend_strength": 0.1315588340833726,
      "trend_linearity": 0.00010829553722244438,
      "seasonal_strength": 0.038055444769786444,
      "seasonal_correlation": 0.09469349086541451,
      "residual_autocorr_lag1": 0.10256858595752623,
      "spectral_entropy": 795.1573188937397
    },
    "min": {
      "trend_strength": 0.5128714784138115,
      "trend_linearity": -0.00024559609519679077,
      "seasonal_strength": 0.0,
      "seasonal_correlation": 0.2939362612807748,
      "residual_autocorr_lag1": 0.6025697372381861,
      "spectral_entropy": -3663.6950578489823
    },
    "max": {
      "trend_strength": 0.9985626315216677,
      "trend_linearity": 0.00015621255500422783,
      "seasonal_strength": 0.10761212147576571,
      "seasonal_correlation": 0.666426353399447,
      "residual_autocorr_lag1": 0.9656861720499913,
      "spectral_entropy": -996.8163715711071
    }
  }
}