{
  "model": "timesfm2p5",
  "dataset": "ETTh1",
  "method": "BM",
  "ratio": 0.2,
  "term": "long",
  "imputation_method": "forward",
  "n_windows": 15,
  "period": 24,
  "summary": {
    "mean": {
      "trend_strength": 0.8910355593059989,
      "trend_linearity": 2.519860955169285e-05,
      "seasonal_strength": 0.8386097813702986,
      "seasonal_correlation": 0.8859166029204425,
      "residual_autocorr_lag1": 0.8174735171031354,
      "spectral_entropy": 259.79242095533033
    },
    "std": {
      "trend_strength": 0.1736136261856518,
      "trend_linearity": 0.0017497455320635619,
      "seasonal_strength": 0.2275844423136392,
      "seasonal_correlation": 0.21434838772880463,
      "residual_autocorr_lag1": 0.10602284016640781,
      "spectral_entropy": 569.3031477871093
    },
    "min": {
      "trend_strength": 0.35141797396873864,
      "trend_linearity": -0.0027005315459509055,
      "seasonal_strength": 0.30472278080879667,
      "seasonal_correlation": 0.2970748499347771,
      "residual_autocorr_lag1": 0.4856902101099772,
      "spectral_entropy": -427.9325187978764
    },
    "max": {
      "trend_strength": 0.9918224794529579,
      "trend_linearity": 0.005050320516973284,
      "seasonal_strength": 0.9924940599599693,
      "seasonal_correlation": 0.9967892774149729,
      "residual_autocorr_lag1": 0.9311379207191096,
      "spectral_entropy": 1461.4786399761647
    }
  }
}