{
  "model": "kairos50m",
  "dataset": "current_velocity_15T",
  "method": "BM",
  "ratio": 0.3,
  "term": "long",
  "imputation_method": "linear",
  "n_windows": 15,
  "period": 96,
  "summary": {
    "mean": {
      "trend_strength": 0.8758378332494837,
      "trend_linearity": 0.00010433216280204865,
      "seasonal_strength": 0.05363000281492831,
      "seasonal_correlation": 0.4830260003825076,
      "residual_autocorr_lag1": 0.9509171878101161,
      "spectral_entropy": -2076.255978927343
    },
    "std": {
      "trend_strength": 0.10797677060763393,
      "trend_linearity": 0.00024984053301556184,
      "seasonal_strength": 0.08581445667837301,
      "seasonal_correlation": 0.18423128507034267,
      "residual_autocorr_lag1": 0.05193171371509023,
      "spectral_entropy": 735.30417397034
    },
    "min": {
      "trend_strength": 0.6292139277370803,
      "trend_linearity": -5.183953285785435e-05,
      "seasonal_strength": 0.0,
      "seasonal_correlation": 0.1002103940632475,
      "residual_autocorr_lag1": 0.8044625181084466,
      "spectral_entropy": -3596.631913701853
    },
    "max": {
      "trend_strength": 0.9963558060331077,
      "trend_linearity": 0.00100461888924779,
      "seasonal_strength": 0.27297095731494825,
      "seasonal_correlation": 0.7612265502801416,
      "residual_autocorr_lag1": 0.9949688788288055,
      "spectral_entropy": -371.8349728632824
    }
  }
}