{
  "model": "kairos50m",
  "dataset": "EWELD_Load_15T",
  "method": "BM",
  "ratio": 0.1,
  "term": "long",
  "imputation_method": "mean",
  "n_windows": 18,
  "period": 96,
  "summary": {
    "mean": {
      "trend_strength": 0.3930296500838544,
      "trend_linearity": 0.010787895030551081,
      "seasonal_strength": 0.976282308977654,
      "seasonal_correlation": 0.9961208886458243,
      "residual_autocorr_lag1": 0.9248982702049326,
      "spectral_entropy": 4099.688443469317
    },
    "std": {
      "trend_strength": 0.23332055544359173,
      "trend_linearity": 0.06325581256545909,
      "seasonal_strength": 0.025719671338572333,
      "seasonal_correlation": 0.005259839419062957,
      "residual_autocorr_lag1": 0.03732292049879888,
      "spectral_entropy": 112.48214483669398
    },
    "min": {
      "trend_strength": 0.005171001028351108,
      "trend_linearity": -0.05463886578783751,
      "seasonal_strength": 0.8856461909576059,
      "seasonal_correlation": 0.9769479380910174,
      "residual_autocorr_lag1": 0.8633243209817729,
      "spectral_entropy": 3705.52599486628
    },
    "max": {
      "trend_strength": 0.79164944390517,
      "trend_linearity": 0.22252527723765864,
      "seasonal_strength": 0.9962827221237737,
      "seasonal_correlation": 0.9994533402540826,
      "residual_autocorr_lag1": 0.9843060662310515,
      "spectral_entropy": 4226.948242704516
    }
  }
}