{
  "model": "kairos50m",
  "dataset": "Port_Activity_D",
  "method": "BM",
  "ratio": 0.3,
  "term": "long",
  "imputation_method": "mean",
  "n_windows": 3,
  "period": 7,
  "summary": {
    "mean": {
      "trend_strength": 0.8856167256063197,
      "trend_linearity": -0.7553680380398277,
      "seasonal_strength": 0.21158035718160006,
      "seasonal_correlation": 0.050187836996367585,
      "residual_autocorr_lag1": 0.44794457771635926,
      "spectral_entropy": 2884.8151209704088
    },
    "std": {
      "trend_strength": 0.09156763874785591,
      "trend_linearity": 0.4232179926554424,
      "seasonal_strength": 0.15283454654244338,
      "seasonal_correlation": 0.010013741888669022,
      "residual_autocorr_lag1": 0.19299269821657877,
      "spectral_entropy": 186.42668296213668
    },
    "min": {
      "trend_strength": 0.7589276984271056,
      "trend_linearity": -1.1066124411322646,
      "seasonal_strength": 0.0,
      "seasonal_correlation": 0.04071274330072044,
      "residual_autocorr_lag1": 0.2191252867242521,
      "spectral_entropy": 2635.4846927127746
    },
    "max": {
      "trend_strength": 0.9721855043742922,
      "trend_linearity": -0.16005460364125212,
      "seasonal_strength": 0.35561857188448487,
      "seasonal_correlation": 0.06404017893313077,
      "residual_autocorr_lag1": 0.6911974279217619,
      "spectral_entropy": 3083.6970134070434
    }
  }
}