{
  "model": "chronos2",
  "dataset": "weather",
  "method": "BM",
  "ratio": 0.2,
  "term": "medium",
  "imputation_method": "mean",
  "n_windows": 20,
  "period": 144,
  "summary": {
    "mean": {
      "trend_strength": 0.389685610327769,
      "trend_linearity": -0.004919983432371269,
      "seasonal_strength": 0.8822558658198055,
      "seasonal_correlation": 0.765884101337904,
      "residual_autocorr_lag1": 0.827918964444395,
      "spectral_entropy": 1215.3565450094527
    },
    "std": {
      "trend_strength": 0.26437580962184554,
      "trend_linearity": 0.012751174935518195,
      "seasonal_strength": 0.13093199651644194,
      "seasonal_correlation": 0.327508947400755,
      "residual_autocorr_lag1": 0.24255143048452607,
      "spectral_entropy": 420.0204366629287
    },
    "min": {
      "trend_strength": 0.0,
      "trend_linearity": -0.04615443952152902,
      "seasonal_strength": 0.5416857080999669,
      "seasonal_correlation": 0.06702627681925738,
      "residual_autocorr_lag1": 0.22938961043487124,
      "spectral_entropy": 532.7412647971032
    },
    "max": {
      "trend_strength": 0.8352081928123463,
      "trend_linearity": 0.010384749411978119,
      "seasonal_strength": 0.9936942488075962,
      "seasonal_correlation": 0.9988932564134223,
      "residual_autocorr_lag1": 0.9913187005977918,
      "spectral_entropy": 2028.4107336794582
    }
  }
}