{
  "model": "visiontspp",
  "window_type": "history",
  "total_combinations": 314,
  "clean_combinations": 26,
  "imputed_combinations": 288,
  "overall_summary": {
    "mean": {
      "trend_strength": 0.518888515036617,
      "trend_linearity": 1.747746882139073,
      "seasonal_strength": 0.43442092968676244,
      "seasonal_correlation": 0.5335336753576497,
      "residual_autocorr_lag1": 0.6788036203665555,
      "spectral_entropy": 15627.709048659217
    },
    "std": {
      "trend_strength": 0.2975482698226447,
      "trend_linearity": 5.827123430924658,
      "seasonal_strength": 0.2739564212077858,
      "seasonal_correlation": 0.31836238568180686,
      "residual_autocorr_lag1": 0.3293733527864924,
      "spectral_entropy": 14476.885744913208
    },
    "min": {
      "trend_strength": 0.0,
      "trend_linearity": -1.3034778629376962,
      "seasonal_strength": 0.0,
      "seasonal_correlation": 0.005159036165121752,
      "residual_autocorr_lag1": -0.046787788560566985,
      "spectral_entropy": -7361.865440363834
    },
    "max": {
      "trend_strength": 0.9985636371888281,
      "trend_linearity": 29.79696881054477,
      "seasonal_strength": 0.9740586597343155,
      "seasonal_correlation": 0.9741323401818414,
      "residual_autocorr_lag1": 0.9841341923664318,
      "spectral_entropy": 61932.25336814458
    },
    "count": {
      "trend_strength": 314,
      "trend_linearity": 314,
      "seasonal_strength": 314,
      "seasonal_correlation": 314,
      "residual_autocorr_lag1": 314,
      "spectral_entropy": 314
    }
  },
  "clean_summary": {
    "mean": {
      "trend_strength": 0.5702028094042852,
      "trend_linearity": 1.7412067068927983,
      "seasonal_strength": 0.5331275903492202,
      "seasonal_correlation": 0.6062505329928475,
      "residual_autocorr_lag1": 0.6553780034362885,
      "spectral_entropy": 14813.458938095935
    },
    "std": {
      "trend_strength": 0.2947460689845519,
      "trend_linearity": 5.860286891476342,
      "seasonal_strength": 0.3060683563469571,
      "seasonal_correlation": 0.3424155780525968,
      "residual_autocorr_lag1": 0.33783277303904985,
      "spectral_entropy": 13970.895067266563
    },
    "min": {
      "trend_strength": 0.01226221331037125,
      "trend_linearity": -0.19304135533914982,
      "seasonal_strength": 0.004458484322484302,
      "seasonal_correlation": 0.0113595267398319,
      "residual_autocorr_lag1": -0.046787788560566985,
      "spectral_entropy": -7294.2195202006005
    },
    "max": {
      "trend_strength": 0.9985636371888281,
      "trend_linearity": 28.323114644899952,
      "seasonal_strength": 0.9740586597343155,
      "seasonal_correlation": 0.9741323401818414,
      "residual_autocorr_lag1": 0.9811651829247622,
      "spectral_entropy": 60179.20799430959
    },
    "count": {
      "trend_strength": 26,
      "trend_linearity": 26,
      "seasonal_strength": 26,
      "seasonal_correlation": 26,
      "residual_autocorr_lag1": 26,
      "spectral_entropy": 26
    }
  },
  "imputed_summary": {
    "mean": {
      "trend_strength": 0.5142559745728692,
      "trend_linearity": 1.7483373146265837,
      "seasonal_strength": 0.4255099117102905,
      "seasonal_correlation": 0.5269689590433609,
      "residual_autocorr_lag1": 0.6809184330060933,
      "spectral_entropy": 15701.217739196181
    },
    "std": {
      "trend_strength": 0.2973644790927099,
      "trend_linearity": 5.824119852511011,
      "seasonal_strength": 0.26909412706010327,
      "seasonal_correlation": 0.3152765276267502,
      "residual_autocorr_lag1": 0.32851674012808546,
      "spectral_entropy": 14519.450725644623
    },
    "min": {
      "trend_strength": 0.0,
      "trend_linearity": -1.3034778629376962,
      "seasonal_strength": 0.0,
      "seasonal_correlation": 0.005159036165121752,
      "residual_autocorr_lag1": -0.03672407178333906,
      "spectral_entropy": -7361.865440363834
    },
    "max": {
      "trend_strength": 0.9984786623350744,
      "trend_linearity": 29.79696881054477,
      "seasonal_strength": 0.9639384103125641,
      "seasonal_correlation": 0.9702442604289901,
      "residual_autocorr_lag1": 0.9841341923664318,
      "spectral_entropy": 61932.25336814458
    },
    "count": {
      "trend_strength": 288,
      "trend_linearity": 288,
      "seasonal_strength": 288,
      "seasonal_correlation": 288,
      "residual_autocorr_lag1": 288,
      "spectral_entropy": 288
    }
  }
}