{
  "model": "kairos23m",
  "dataset": "ETTh1",
  "method": "BM",
  "ratio": 0.1,
  "term": "long",
  "imputation_method": "backward",
  "n_windows": 15,
  "period": 24,
  "summary": {
    "mean": {
      "trend_strength": 0.9038939973506641,
      "trend_linearity": 9.426397077915585e-05,
      "seasonal_strength": 0.948011354961406,
      "seasonal_correlation": 0.9546173006662587,
      "residual_autocorr_lag1": 0.8791567886904963,
      "spectral_entropy": 514.907696822034
    },
    "std": {
      "trend_strength": 0.0925265527725094,
      "trend_linearity": 0.0010385307250163182,
      "seasonal_strength": 0.053534341763495044,
      "seasonal_correlation": 0.12744318171163452,
      "residual_autocorr_lag1": 0.046932424021817284,
      "spectral_entropy": 379.8137903174262
    },
    "min": {
      "trend_strength": 0.648130523159554,
      "trend_linearity": -0.001544593026997144,
      "seasonal_strength": 0.8085289260141568,
      "seasonal_correlation": 0.4835537101505078,
      "residual_autocorr_lag1": 0.7695727650770532,
      "spectral_entropy": -53.76258881977208
    },
    "max": {
      "trend_strength": 0.9839963338410943,
      "trend_linearity": 0.0016543542849095031,
      "seasonal_strength": 0.9888193445279111,
      "seasonal_correlation": 0.9978626758014422,
      "residual_autocorr_lag1": 0.9350579266775754,
      "spectral_entropy": 1184.0398799471964
    }
  }
}