{
  "model": "timesfm2p0",
  "dataset": "Finland_Traffic_15T",
  "method": "BM",
  "ratio": 0.1,
  "term": "long",
  "imputation_method": "linear",
  "n_windows": 20,
  "period": 96,
  "summary": {
    "mean": {
      "trend_strength": 0.031602891886542986,
      "trend_linearity": 0.01056676679373389,
      "seasonal_strength": 0.9034074772989291,
      "seasonal_correlation": 0.969301616415987,
      "residual_autocorr_lag1": 0.9292129613889847,
      "spectral_entropy": 3919.863885791274
    },
    "std": {
      "trend_strength": 0.04093214433533342,
      "trend_linearity": 0.02119369221025675,
      "seasonal_strength": 0.035841623422542615,
      "seasonal_correlation": 0.026353770322219045,
      "residual_autocorr_lag1": 0.037799690586882,
      "spectral_entropy": 114.77774801006453
    },
    "min": {
      "trend_strength": 0.0,
      "trend_linearity": -0.027869858496353237,
      "seasonal_strength": 0.8550139517819029,
      "seasonal_correlation": 0.9095032754434017,
      "residual_autocorr_lag1": 0.8447634859371175,
      "spectral_entropy": 3709.7947614851546
    },
    "max": {
      "trend_strength": 0.1303327944352538,
      "trend_linearity": 0.053841831370875275,
      "seasonal_strength": 0.9825917118842589,
      "seasonal_correlation": 0.9979683216818962,
      "residual_autocorr_lag1": 0.9746278403394294,
      "spectral_entropy": 4133.866920401451
    }
  }
}