{
  "model": "timesfm2p0",
  "dataset": "Finland_Traffic_15T",
  "method": "BM",
  "ratio": 0.3,
  "term": "long",
  "imputation_method": "mean",
  "n_windows": 20,
  "period": 96,
  "summary": {
    "mean": {
      "trend_strength": 0.1054478265939699,
      "trend_linearity": -0.007458125164038776,
      "seasonal_strength": 0.8966810292490747,
      "seasonal_correlation": 0.9718900919053551,
      "residual_autocorr_lag1": 0.946473661418793,
      "spectral_entropy": 3763.164499414886
    },
    "std": {
      "trend_strength": 0.11520337045238645,
      "trend_linearity": 0.02994744057902971,
      "seasonal_strength": 0.044623405888867915,
      "seasonal_correlation": 0.025474137026182002,
      "residual_autocorr_lag1": 0.029063522481498755,
      "spectral_entropy": 197.69068886652832
    },
    "min": {
      "trend_strength": 0.0,
      "trend_linearity": -0.06447251236355168,
      "seasonal_strength": 0.7921007495812555,
      "seasonal_correlation": 0.8953831617949568,
      "residual_autocorr_lag1": 0.8928053685842207,
      "spectral_entropy": 3228.56524980877
    },
    "max": {
      "trend_strength": 0.48841378026349047,
      "trend_linearity": 0.044197242272842226,
      "seasonal_strength": 0.9780076693041473,
      "seasonal_correlation": 0.9966132132133422,
      "residual_autocorr_lag1": 0.9849685324708635,
      "spectral_entropy": 4147.109067561732
    }
  }
}