{
  "model": "timesfm2p0",
  "dataset": "Supply_Chain_Customer_D",
  "method": "BM",
  "ratio": 0.1,
  "term": "long",
  "imputation_method": "forward",
  "n_windows": 3,
  "period": 7,
  "summary": {
    "mean": {
      "trend_strength": 0.9266623082145592,
      "trend_linearity": 20.02067613492447,
      "seasonal_strength": 0.989037924588214,
      "seasonal_correlation": 0.9614324726257433,
      "residual_autocorr_lag1": 0.24222035391986108,
      "spectral_entropy": 5111.080455691324
    },
    "std": {
      "trend_strength": 0.01570028036649106,
      "trend_linearity": 6.03702859340234,
      "seasonal_strength": 0.004445472216789304,
      "seasonal_correlation": 0.017239602854987747,
      "residual_autocorr_lag1": 0.04555639771779869,
      "spectral_entropy": 22.926764990808678
    },
    "min": {
      "trend_strength": 0.9046002183386217,
      "trend_linearity": 12.307262718400871,
      "seasonal_strength": 0.9827871864297497,
      "seasonal_correlation": 0.9370717248108926,
      "residual_autocorr_lag1": 0.18814062681431826,
      "spectral_entropy": 5079.101902003285
    },
    "max": {
      "trend_strength": 0.9398604590819133,
      "trend_linearity": 27.046927204081296,
      "seasonal_strength": 0.9927459935911698,
      "seasonal_correlation": 0.9744621605637196,
      "residual_autocorr_lag1": 0.29958537858804773,
      "spectral_entropy": 5131.704806151976
    }
  }
}