{
  "model": "visiontspp",
  "dataset": "NE_China_Wind_H",
  "method": "BM",
  "ratio": 0.2,
  "term": "long",
  "imputation_method": "backward",
  "n_windows": 8,
  "period": 24,
  "summary": {
    "mean": {
      "trend_strength": 0.9588954293655441,
      "trend_linearity": -0.00046954453394861207,
      "seasonal_strength": 0.0012707688498299619,
      "seasonal_correlation": 0.09093454973868266,
      "residual_autocorr_lag1": 0.946370964629176,
      "spectral_entropy": -413.0479993300004
    },
    "std": {
      "trend_strength": 0.06855515444958195,
      "trend_linearity": 0.0007588500105540678,
      "seasonal_strength": 0.003026000139577111,
      "seasonal_correlation": 0.0697212160215079,
      "residual_autocorr_lag1": 0.03973736921435643,
      "spectral_entropy": 451.5580957540057
    },
    "min": {
      "trend_strength": 0.780262582124975,
      "trend_linearity": -0.0018190598295254163,
      "seasonal_strength": 0.0,
      "seasonal_correlation": 0.03071650978654817,
      "residual_autocorr_lag1": 0.8700660290966422,
      "spectral_entropy": -1281.2357056901449
    },
    "max": {
      "trend_strength": 0.9981765931028314,
      "trend_linearity": 0.0003143371167511866,
      "seasonal_strength": 0.009238362063165306,
      "seasonal_correlation": 0.24833860889207598,
      "residual_autocorr_lag1": 0.9830044204612759,
      "spectral_entropy": 88.22355336225684
    }
  }
}