{
  "success": true,
  "dir_info": {
    "dataset": "ETTh1",
    "method": "BM",
    "block_length": 50,
    "ratio": 0.1,
    "term": "short"
  },
  "imputation_method": "linear",
  "n_windows": 20,
  "period": 24,
  "summary": {
    "mean": {
      "trend_strength": 0.9259466643840282,
      "trend_linearity": 0.008618052501200717,
      "seasonal_strength": 0.9965048846732799,
      "seasonal_correlation": 0.9802171056910793,
      "residual_autocorr_lag1": 0.22110869741989664,
      "spectral_entropy": -10.639212168525487
    },
    "std": {
      "trend_strength": 0.16973039014986904,
      "trend_linearity": 0.02413616433012178,
      "seasonal_strength": 0.005254279070978495,
      "seasonal_correlation": 0.017616685607611367,
      "residual_autocorr_lag1": 0.23436795338289956,
      "spectral_entropy": 32.72246074834503
    },
    "min": {
      "trend_strength": 0.2784851637538447,
      "trend_linearity": -0.03713914669083985,
      "seasonal_strength": 0.9780374405804454,
      "seasonal_correlation": 0.9167329535603073,
      "residual_autocorr_lag1": -0.02618124118476728,
      "spectral_entropy": -61.797849982529584
    },
    "max": {
      "trend_strength": 1.0,
      "trend_linearity": 0.06261208511904744,
      "seasonal_strength": 1.0,
      "seasonal_correlation": 0.9977353532755036,
      "residual_autocorr_lag1": 0.5757101405009163,
      "spectral_entropy": 55.844170046810525
    }
  },
  "window_results": [
    {
      "success": true,
      "window_idx": 0,
      "dataset": "ETTh1",
      "metrics": {
        "trend_strength": 0.9998995735130481,
        "trend_linearity": -0.03713914669083985,
        "seasonal_strength": 0.9998800306096354,
        "seasonal_correlation": 0.9828758123256061,
        "residual_autocorr_lag1": -0.021719858155649516,
        "spectral_entropy": 12.499579404436632
      },
      "n_series": 1
    },
    {
      "success": true,
      "window_idx": 1,
      "dataset": "ETTh1",
      "metrics": {
        "trend_strength": 0.9899330308067209,
        "trend_linearity": 0.06261208511904744,
        "seasonal_strength": 0.9780374405804454,
        "seasonal_correlation": 0.9692972464395764,
        "residual_autocorr_lag1": 0.44009841169481606,
        "spectral_entropy": 55.844170046810525
      },
      "n_series": 1
    },
    {
      "success": true,
      "window_idx": 10,
      "dataset": "ETTh1",
      "metrics": {
        "trend_strength": 0.656192078531489,
        "trend_linearity": -0.007873302446172013,
        "seasonal_strength": 0.9935637883727062,
        "seasonal_correlation": 0.9977353532755036,
        "residual_autocorr_lag1": 0.5271272683868269,
        "spectral_entropy": -14.78102639171364
      },
      "n_series": 1
    },
    {
      "success": true,
      "window_idx": 11,
      "dataset": "ETTh1",
      "metrics": {
        "trend_strength": 0.8891107565419614,
        "trend_linearity": 0.012787406992412669,
        "seasonal_strength": 0.9912579136918295,
        "seasonal_correlation": 0.9790334021171462,
        "residual_autocorr_lag1": 0.1637213124440289,
        "spectral_entropy": -20.206732657279957
      },
      "n_series": 1
    },
    {
      "success": true,
      "window_idx": 12,
      "dataset": "ETTh1",
      "metrics": {
        "trend_strength": 1.0,
        "trend_linearity": 0.006036899305555475,
        "seasonal_strength": 1.0,
        "seasonal_correlation": 0.9841781975481848,
        "residual_autocorr_lag1": 0.037821750321750267,
        "spectral_entropy": -39.16703833292681
      },
      "n_series": 1
    },
    {
      "success": true,
      "window_idx": 13,
      "dataset": "ETTh1",
      "metrics": {
        "trend_strength": 0.973306896860302,
        "trend_linearity": -0.02545972872314418,
        "seasonal_strength": 0.9948891911649724,
        "seasonal_correlation": 0.9952205530093496,
        "residual_autocorr_lag1": 0.5702831434421554,
        "spectral_entropy": 15.639951583291865
      },
      "n_series": 1
    },
    {
      "success": true,
      "window_idx": 14,
      "dataset": "ETTh1",
      "metrics": {
        "trend_strength": 1.0,
        "trend_linearity": 0.002994601562499908,
        "seasonal_strength": 1.0,
        "seasonal_correlation": 0.9917144545675556,
        "residual_autocorr_lag1": -0.02618124118476728,
        "spectral_entropy": -54.13322042280618
      },
      "n_series": 1
    },
    {
      "success": true,
      "window_idx": 15,
      "dataset": "ETTh1",
      "metrics": {
        "trend_strength": 1.0,
        "trend_linearity": 0.014477092013888854,
        "seasonal_strength": 1.0,
        "seasonal_correlation": 0.9874999468926567,
        "residual_autocorr_lag1": 0.46969696969696956,
        "spectral_entropy": -15.854407027149097
      },
      "n_series": 1
    },
    {
      "success": true,
      "window_idx": 16,
      "dataset": "ETTh1",
      "metrics": {
        "trend_strength": 1.0,
        "trend_linearity": -0.026475154513889165,
        "seasonal_strength": 1.0,
        "seasonal_correlation": 0.9934715724789102,
        "residual_autocorr_lag1": 0.4978160501803694,
        "spectral_entropy": 14.797169235326965
      },
      "n_series": 1
    },
    {
      "success": true,
      "window_idx": 17,
      "dataset": "ETTh1",
      "metrics": {
        "trend_strength": 0.9486596864325237,
        "trend_linearity": 0.00996010354179758,
        "seasonal_strength": 0.9925343688631288,
        "seasonal_correlation": 0.9915798633051355,
        "residual_autocorr_lag1": 0.27797401484069034,
        "spectral_entropy": -22.947269490756725
      },
      "n_series": 1
    },
    {
      "success": true,
      "window_idx": 18,
      "dataset": "ETTh1",
      "metrics": {
        "trend_strength": 1.0,
        "trend_linearity": 0.04636934253472212,
        "seasonal_strength": 1.0,
        "seasonal_correlation": 0.958217524796932,
        "residual_autocorr_lag1": 0.4433931377684652,
        "spectral_entropy": 35.471778418517445
      },
      "n_series": 1
    },
    {
      "success": true,
      "window_idx": 19,
      "dataset": "ETTh1",
      "metrics": {
        "trend_strength": 1.0,
        "trend_linearity": -0.0035810911458335356,
        "seasonal_strength": 1.0,
        "seasonal_correlation": 0.9167329535603073,
        "residual_autocorr_lag1": 0.5757101405009163,
        "spectral_entropy": -61.797849982529584
      },
      "n_series": 1
    },
    {
      "success": true,
      "window_idx": 2,
      "dataset": "ETTh1",
      "metrics": {
        "trend_strength": 0.9990104403817428,
        "trend_linearity": 0.051260698863636406,
        "seasonal_strength": 0.9978660293149639,
        "seasonal_correlation": 0.9906614431768178,
        "residual_autocorr_lag1": -0.0202278417568298,
        "spectral_entropy": 44.70825492713378
      },
      "n_series": 1
    },
    {
      "success": true,
      "window_idx": 3,
      "dataset": "ETTh1",
      "metrics": {
        "trend_strength": 1.0,
        "trend_linearity": 0.014294804687499992,
        "seasonal_strength": 1.0,
        "seasonal_correlation": 0.970518970233531,
        "residual_autocorr_lag1": 0.09615384615384616,
        "spectral_entropy": -8.694601326980013
      },
      "n_series": 1
    },
    {
      "success": true,
      "window_idx": 4,
      "dataset": "ETTh1",
      "metrics": {
        "trend_strength": 0.9950578901047866,
        "trend_linearity": 0.023505056340579682,
        "seasonal_strength": 0.9964062112724641,
        "seasonal_correlation": 0.9724270257350123,
        "residual_autocorr_lag1": -0.021719858156042916,
        "spectral_entropy": 19.351374231325053
      },
      "n_series": 1
    },
    {
      "success": true,
      "window_idx": 5,
      "dataset": "ETTh1",
      "metrics": {
        "trend_strength": 1.0,
        "trend_linearity": 0.0013843697916666221,
        "seasonal_strength": 1.0,
        "seasonal_correlation": 0.9763853139088465,
        "residual_autocorr_lag1": 0.03247816593886463,
        "spectral_entropy": -40.814862751918135
      },
      "n_series": 1
    },
    {
      "success": true,
      "window_idx": 6,
      "dataset": "ETTh1",
      "metrics": {
        "trend_strength": 0.2784851637538447,
        "trend_linearity": 0.0012038940217391244,
        "seasonal_strength": 0.9943522276230726,
        "seasonal_correlation": 0.9920006122572143,
        "residual_autocorr_lag1": -0.00044326241136060437,
        "spectral_entropy": -34.55802343756649
      },
      "n_series": 1
    },
    {
      "success": true,
      "window_idx": 7,
      "dataset": "ETTh1",
      "metrics": {
        "trend_strength": 0.96203707114191,
        "trend_linearity": 0.005518325262729791,
        "seasonal_strength": 0.9919625490863887,
        "seasonal_correlation": 0.9900651196859376,
        "residual_autocorr_lag1": -0.02541713376628932,
        "spectral_entropy": -48.54515808288335
      },
      "n_series": 1
    },
    {
      "success": true,
      "window_idx": 8,
      "dataset": "ETTh1",
      "metrics": {
        "trend_strength": 1.0,
        "trend_linearity": 0.01789145486111088,
        "seasonal_strength": 1.0,
        "seasonal_correlation": 0.983734857457597,
        "residual_autocorr_lag1": 0.4057216656230432,
        "spectral_entropy": -17.772636047892657
      },
      "n_series": 1
    },
    {
      "success": true,
      "window_idx": 9,
      "dataset": "ETTh1",
      "metrics": {
        "trend_strength": 0.827240699612235,
        "trend_linearity": 0.002593338645006557,
        "seasonal_strength": 0.9993479428859952,
        "seasonal_correlation": 0.980991891049765,
        "residual_autocorr_lag1": -0.00011273316387037883,
        "spectral_entropy": -31.823695264949418
      },
      "n_series": 1
    }
  ]
}