{
  "success": true,
  "dir_info": {
    "dataset": "exchange_rate",
    "method": "BM",
    "block_length": 50,
    "ratio": 0.1,
    "term": "long"
  },
  "imputation_method": "forward",
  "n_windows": 11,
  "period": 7,
  "summary": {
    "mean": {
      "trend_strength": 0.9997832160550728,
      "trend_linearity": -8.216128102420131e-05,
      "seasonal_strength": 0.14125363851283035,
      "seasonal_correlation": 0.12842760645157367,
      "residual_autocorr_lag1": 0.23797374965883478,
      "spectral_entropy": -1219.1738269351308
    },
    "std": {
      "trend_strength": 0.0002000539366825985,
      "trend_linearity": 0.0002147223930016117,
      "seasonal_strength": 0.05920321608778487,
      "seasonal_correlation": 0.06529849334485756,
      "residual_autocorr_lag1": 0.08333059121985084,
      "spectral_entropy": 357.8731643868501
    },
    "min": {
      "trend_strength": 0.999246506694315,
      "trend_linearity": -0.0005416740877168387,
      "seasonal_strength": 0.03659063594555678,
      "seasonal_correlation": 0.028047984907607577,
      "residual_autocorr_lag1": 0.11358515366804843,
      "spectral_entropy": -2105.6122488613005
    },
    "max": {
      "trend_strength": 0.9999756133693366,
      "trend_linearity": 0.00024450052512287263,
      "seasonal_strength": 0.24021397180153514,
      "seasonal_correlation": 0.22269332440430242,
      "residual_autocorr_lag1": 0.37286764970254554,
      "spectral_entropy": -659.2718903336141
    }
  },
  "window_results": [
    {
      "success": true,
      "window_idx": 0,
      "dataset": "exchange_rate",
      "metrics": {
        "trend_strength": 0.9998891393555092,
        "trend_linearity": 0.00024450052512287263,
        "seasonal_strength": 0.08631227639959083,
        "seasonal_correlation": 0.05156227591720739,
        "residual_autocorr_lag1": 0.22561624016500828,
        "spectral_entropy": -986.598419330841
      },
      "n_series": 1
    },
    {
      "success": true,
      "window_idx": 1,
      "dataset": "exchange_rate",
      "metrics": {
        "trend_strength": 0.9998332646633932,
        "trend_linearity": 0.00013668404572044382,
        "seasonal_strength": 0.09609099655094522,
        "seasonal_correlation": 0.16352204988215338,
        "residual_autocorr_lag1": 0.11358515366804843,
        "spectral_entropy": -1276.4491755884033
      },
      "n_series": 1
    },
    {
      "success": true,
      "window_idx": 10,
      "dataset": "exchange_rate",
      "metrics": {
        "trend_strength": 0.999717856482815,
        "trend_linearity": 9.18450090422016e-05,
        "seasonal_strength": 0.24021397180153514,
        "seasonal_correlation": 0.22269332440430242,
        "residual_autocorr_lag1": 0.15394597879373106,
        "spectral_entropy": -1422.880455465286
      },
      "n_series": 1
    },
    {
      "success": true,
      "window_idx": 2,
      "dataset": "exchange_rate",
      "metrics": {
        "trend_strength": 0.9998512679263661,
        "trend_linearity": -1.243247178938842e-05,
        "seasonal_strength": 0.21272013698471026,
        "seasonal_correlation": 0.028047984907607577,
        "residual_autocorr_lag1": 0.37286764970254554,
        "spectral_entropy": -2105.6122488613005
      },
      "n_series": 1
    },
    {
      "success": true,
      "window_idx": 3,
      "dataset": "exchange_rate",
      "metrics": {
        "trend_strength": 0.9997963878487599,
        "trend_linearity": -0.00014549122867839757,
        "seasonal_strength": 0.1519110371167529,
        "seasonal_correlation": 0.12479482738849879,
        "residual_autocorr_lag1": 0.25655565570393557,
        "spectral_entropy": -1172.1208454498776
      },
      "n_series": 1
    },
    {
      "success": true,
      "window_idx": 4,
      "dataset": "exchange_rate",
      "metrics": {
        "trend_strength": 0.9999756133693366,
        "trend_linearity": -0.0005416740877168387,
        "seasonal_strength": 0.13819635952062304,
        "seasonal_correlation": 0.18972497946893796,
        "residual_autocorr_lag1": 0.19731060692263097,
        "spectral_entropy": -659.2718903336141
      },
      "n_series": 1
    },
    {
      "success": true,
      "window_idx": 5,
      "dataset": "exchange_rate",
      "metrics": {
        "trend_strength": 0.999246506694315,
        "trend_linearity": 0.0001018765496327685,
        "seasonal_strength": 0.20574001909135575,
        "seasonal_correlation": 0.09750906661756804,
        "residual_autocorr_lag1": 0.17152548165005152,
        "spectral_entropy": -1348.2965862695437
      },
      "n_series": 1
    },
    {
      "success": true,
      "window_idx": 6,
      "dataset": "exchange_rate",
      "metrics": {
        "trend_strength": 0.9998018541570132,
        "trend_linearity": -0.0001665829838770941,
        "seasonal_strength": 0.03659063594555678,
        "seasonal_correlation": 0.09737852060167121,
        "residual_autocorr_lag1": 0.3421689694244652,
        "spectral_entropy": -1409.9417497091963
      },
      "n_series": 1
    },
    {
      "success": true,
      "window_idx": 7,
      "dataset": "exchange_rate",
      "metrics": {
        "trend_strength": 0.9995977459434733,
        "trend_linearity": -9.895194714505205e-05,
        "seasonal_strength": 0.12324736526435398,
        "seasonal_correlation": 0.1593481974685829,
        "residual_autocorr_lag1": 0.2747255286229312,
        "spectral_entropy": -1132.3732661524552
      },
      "n_series": 1
    },
    {
      "success": true,
      "window_idx": 8,
      "dataset": "exchange_rate",
      "metrics": {
        "trend_strength": 0.9999478136989066,
        "trend_linearity": -0.00025734545576534855,
        "seasonal_strength": 0.09369025704777889,
        "seasonal_correlation": 0.05561053255658295,
        "residual_autocorr_lag1": 0.34503838355574856,
        "spectral_entropy": -921.0197132994937
      },
      "n_series": 1
    },
    {
      "success": true,
      "window_idx": 9,
      "dataset": "exchange_rate",
      "metrics": {
        "trend_strength": 0.9999579264659122,
        "trend_linearity": -0.0002562020458123815,
        "seasonal_strength": 0.16907696791793114,
        "seasonal_correlation": 0.22251191175419766,
        "residual_autocorr_lag1": 0.16437159803808615,
        "spectral_entropy": -976.3477458264261
      },
      "n_series": 1
    }
  ]
}